poetry_template_plugin/plugin.py
poetry_template_plugin-0.1.10.dist-info/METADATA
poetry_template_plugin-0.1.10.dist-info/WHEEL
poetry_template_plugin-0.1.10.dist-info/entry_points.txt
poetry_template_plugin-0.1.10.dist-info/RECORD
