Metadata-Version: 2.1
Name: poetry-template-plugin
Version: 0.1.10
Summary: 
Author: aachurin
Author-email: aachurin@gmail.com
Requires-Python: >=3.10,<4.0
Classifier: Programming Language :: Python :: 3
Classifier: Programming Language :: Python :: 3.10
Classifier: Programming Language :: Python :: 3.11
Requires-Dist: merge3 (>=0.0.13,<0.0.14)
Requires-Dist: poetry (>=1.2,<2.0)
Requires-Dist: tomlkit (>=0.11.1,<1.0.0)
